argparsenv/__init__.py
argparsenv/argparsenv.py
argparsenv-1.0.7.dist-info/LICENSE
argparsenv-1.0.7.dist-info/METADATA
argparsenv-1.0.7.dist-info/WHEEL
argparsenv-1.0.7.dist-info/RECORD
