Metadata-Version: 2.3
Name: argparsenv
Version: 1.0.7
Summary: Extends python's argparser with environment variables
License: MIT
Keywords: cli,environment,arguments
Author: snaeil
Author-email: schnegel@posteo.de
Requires-Python: >=3.11,<4.0
Classifier: Development Status :: 5 - Production/Stable
Classifier: Environment :: Console
Classifier: Intended Audience :: Developers
Classifier: License :: OSI Approved :: MIT License
Classifier: Operating System :: MacOS
Classifier: Operating System :: Microsoft :: Windows
Classifier: Operating System :: POSIX :: Linux
Classifier: Programming Language :: Python :: 3
Classifier: Programming Language :: Python :: 3.11
Classifier: Programming Language :: Python :: 3.12
Classifier: Programming Language :: Python :: 3.13
Classifier: Programming Language :: Python :: 3.10
Classifier: Typing :: Typed
Requires-Dist: overrides (>=7.7.0,<8.0.0)
Requires-Dist: python-dotenv (>=1.0.1,<2.0.0)
Project-URL: Homepage, https://github.com/snaeil/argparsenv
Project-URL: Repository, https://github.com/snaeil/argparsenv
